{
  "project_info": {
    "project_number": "425559907666",
    "firebase_url": "https://forest-of-arms-default-rtdb.firebaseio.com",
    "project_id": "forest-of-arms",
    "storage_bucket": "forest-of-arms.appspot.com"
  },
  "client": [
    {
      "client_info": {
        "mobilesdk_app_id": "1:425559907666:android:7cfcf2c1c162c9d4db2e8b",
        "android_client_info": {
          "package_name": "com.RiceCompany.Forestofarms"
        }
      },
      "oauth_client": [
        {
          "client_id": "425559907666-jq0q2hu2fpf2u7a523v3c3sq9srifj5p.apps.googleusercontent.com",
          "client_type": 3
        }
      ],
      "api_key": [
        {
          "current_key": "AIzaSyBME_cjQ8kDeN8fmaXUsPHFsy3dmxJ2-K4"
        }
      ],
      "services": {
        "appinvite_service": {
          "other_platform_oauth_client": [
            {
              "client_id": "425559907666-jq0q2hu2fpf2u7a523v3c3sq9srifj5p.apps.googleusercontent.com",
              "client_type": 3
            }
          ]
        }
      }
    }
  ],
  "configuration_version": "1"
}